tf2/__init__.py
tf2/cli.py
tf2/test.py
tf2/tf2.py
tf2/executor/__init__.py
tf2/executor/executor.py
tf2/executor/local.py
tf2/terraform/__init__.py
tf2/terraform/loader.py
tf2/terraform/local.py
tf2/terraform/object.py
tf2/terraform/terraform.py
tf2/terraform/util.py
tf2project-0.2.0.dist-info/LICENSE
tf2project-0.2.0.dist-info/METADATA
tf2project-0.2.0.dist-info/WHEEL
tf2project-0.2.0.dist-info/top_level.txt
tf2project-0.2.0.dist-info/zip-safe
tf2project-0.2.0.dist-info/RECORD
