Metadata-Version: 2.1
Name: tf2project
Version: 0.2.0
Summary: Terraform Test Framework
Home-page: https://github.com/tf2project/tf2project
Author: Saeid Bostandoust
Author-email: ssbostan@yahoo.com
License: Apache License 2.0
Project-URL: Documentation, https://tf2project.io
Classifier: Development Status :: 4 - Beta
Classifier: Environment :: Console
Classifier: Intended Audience :: Developers
Classifier: Intended Audience :: Information Technology
Classifier: Intended Audience :: System Administrators
Classifier: License :: OSI Approved :: Apache Software License
Classifier: Programming Language :: Python :: 3 :: Only
Classifier: Topic :: Security
Classifier: Topic :: Software Development :: Bug Tracking
Classifier: Topic :: Software Development :: Testing
License-File: LICENSE
